diclass/__init__.py
diclass/src/flag.py
diclass/src/util.py
diclass-1.3.1.dist-info/LICENSE
diclass-1.3.1.dist-info/METADATA
diclass-1.3.1.dist-info/WHEEL
diclass-1.3.1.dist-info/top_level.txt
diclass-1.3.1.dist-info/RECORD
