Metadata-Version: 2.1
Name: diclass
Version: 1.3.1
Summary: converts python dictoinary to class object
Author: Moses Dastmard
License: UNKNOWN
Platform: UNKNOWN
License-File: LICENSE
